do_latency/__init__.py
do_latency/__main__.py
do_latency/do_latency.py
do_latency/download.py
do_latency/ping.py
do_latency/pyping.py
do_latency-0.4.0.data/data/LICENSE
do_latency-0.4.0.data/data/README.rst
do_latency-0.4.0.dist-info/DESCRIPTION.rst
do_latency-0.4.0.dist-info/METADATA
do_latency-0.4.0.dist-info/RECORD
do_latency-0.4.0.dist-info/WHEEL
do_latency-0.4.0.dist-info/entry_points.txt
do_latency-0.4.0.dist-info/metadata.json
do_latency-0.4.0.dist-info/top_level.txt
