Metadata-Version: 2.0
Name: do-latency
Version: 0.4.0
Summary: Digital Ocean latency checker helps to find fastest DO region from your location.
Home-page: https://github.com/dizballanze/do-latency
Author: Yuri Shikanov
Author-email: dizballanze@gmail.com
License: MIT
Keywords: digital ocean latency ping connection speed ICMP
Platform: UNKNOWN
Classifier: Development Status :: 4 - Beta
Classifier: License :: OSI Approved :: MIT License
Classifier: Programming Language :: Python :: 2.7
Classifier: Programming Language :: Python :: 3
Classifier: Programming Language :: Python :: 3.4
Classifier: Programming Language :: Python :: 3.5
Classifier: Programming Language :: Python :: Implementation :: CPython
Requires-Dist: six (==1.10.0)
Requires-Dist: terminaltables (==2.1.0)
Requires-Dist: tqdm (==4.23.0)
